setup.cfg
setup.py
src/math_util.c
stsci/__init__.py
stsci.sphere.egg-info/PKG-INFO
stsci.sphere.egg-info/SOURCES.txt
stsci.sphere.egg-info/dependency_links.txt
stsci.sphere.egg-info/namespace_packages.txt
stsci.sphere.egg-info/not-zip-safe
stsci.sphere.egg-info/top_level.txt
stsci/sphere/__init__.py
stsci/sphere/graph.py
stsci/sphere/great_circle_arc.py
stsci/sphere/polygon.py
stsci/sphere/vector.py
stsci/sphere/test/__init__.py
stsci/sphere/test/benchmarks.py
stsci/sphere/test/test.py
stsci/sphere/test/test_intersection.py
stsci/sphere/test/test_shared.py
stsci/sphere/test/test_union.py
stsci/sphere/test/test_util.py
stsci/sphere/test/data/1904-66_TAN.fits.gz
stsci/sphere/test/data/2chipA.fits.gz
stsci/sphere/test/data/2chipB.fits.gz
stsci/sphere/test/data/2chipC.fits.gz
stsci/sphere/test/data/difficult_intersections.txt