Metadata-Version: 1.1
Name: stsci.sphere
Version: 0.2
Summary: Python based tools for spherical geometry
Home-page: http://www.stsci.edu/resources/software_hardware/stsci_python
Author: Michael Droettboom
Author-email: help@stsci.edu
License: UNKNOWN
Platform: UNKNOWN
Classifier: Intended Audience :: Science/Research
Classifier: License :: OSI Approved :: BSD License
Classifier: Operating System :: OS Independent
Classifier: Programming Language :: Python
Classifier: Topic :: Scientific/Engineering :: Astronomy
Classifier: Topic :: Software Development :: Libraries :: Python Modules
